simpleroute/__init__.py
simpleroute/router.py
simpleroute-0.0.3.dist-info/METADATA
simpleroute-0.0.3.dist-info/WHEEL
simpleroute-0.0.3.dist-info/licenses/LICENSE
simpleroute-0.0.3.dist-info/RECORD
