Metadata-Version: 2.1
Name: simpleroute
Version: 0.0.3
Summary: A simple router / treelib for python.
Project-URL: Homepage, https://github.com/Xynonners/simpleroute
Project-URL: Bug Tracker, https://github.com/Xynonners/simpleroute/issues
Author: Xynon
License-File: LICENSE
Classifier: Development Status :: 3 - Alpha
Classifier: License :: OSI Approved :: Mozilla Public License 2.0 (MPL 2.0)
Classifier: Operating System :: OS Independent
Classifier: Programming Language :: Python :: 3
Requires-Python: >=3.7
Requires-Dist: rich
